Metadata-Version: 2.1
Name: nspb
Version: 1.2.0
Summary: ProgressBar for python
Home-page: https://github.com/realpython/reader
Author: Alexandre Hachet
Author-email: info@realpython.com
License: MIT
Platform: UNKNOWN
Classifier: License :: OSI Approved :: MIT License
Classifier: Programming Language :: Python :: 3
Classifier: Programming Language :: Python :: 3.7
